psyqlepg/__init__.py
psyqlepg/table.py
psyqlepg/table_info.py
psyqlepg/util.py
psyqlepg/where.py
psyqlepg-0.4.1.dist-info/LICENSE
psyqlepg-0.4.1.dist-info/METADATA
psyqlepg-0.4.1.dist-info/WHEEL
psyqlepg-0.4.1.dist-info/top_level.txt
psyqlepg-0.4.1.dist-info/RECORD
