Metadata-Version: 2.1
Name: psyqlepg
Version: 0.4.1
Summary: Simple SQL library for psycopg3.
Author-email: Damien Bezborodov <dbezborodov@gmail.com>
Project-URL: Homepage, https://github.com/bezborodow/psyqlepg
Project-URL: Bug Tracker, https://github.com/bezborodow/psyqlepg/issues
Classifier: Programming Language :: Python :: 3
Classifier: License :: OSI Approved :: MIT License
Classifier: Operating System :: OS Independent
Requires-Python: >=3.7
License-File: LICENSE
Requires-Dist: psycopg >=3.1
